<?xml version="1.0" encoding="UTF-8"?>
<objects serializationModel="Studio.02.03.00">
	<object class="AudioFile" id="{335603d1-4623-49f0-a63a-21f66609149f}">
		<property name="assetPath">
			<value>environment/ambient/destructible_4.wav</value>
		</property>
		<property name="frequencyInKHz">
			<value>96</value>
		</property>
		<property name="channelCount">
			<value>2</value>
		</property>
		<property name="length">
			<value>1.1538958333333333</value>
		</property>
		<relationship name="masterAssetFolder">
			<destination>{05d4d0d3-5fce-4c76-8799-058a71a4c790}</destination>
		</relationship>
	</object>
</objects>
